jito_async/__init__.py
jito_async/core/__init__.py
jito_async/core/sdk.py
jito_async-0.1.4.dist-info/LICENSE
jito_async-0.1.4.dist-info/METADATA
jito_async-0.1.4.dist-info/WHEEL
jito_async-0.1.4.dist-info/RECORD
