Metadata-Version: 2.3
Name: jito-async
Version: 0.1.4
Summary: Async Python SDK for Jito Block Engine
License: MIT
Keywords: jito,solana,blockchain,async,sdk
Author: ChefJodlak
Requires-Python: >=3.9,<4.0
Classifier: Development Status :: 4 - Beta
Classifier: Intended Audience :: Developers
Classifier: License :: OSI Approved :: MIT License
Classifier: Programming Language :: Python :: 3
Classifier: Programming Language :: Python :: 3.9
Classifier: Programming Language :: Python :: 3.10
Classifier: Programming Language :: Python :: 3.11
Classifier: Programming Language :: Python :: 3.12
Classifier: Programming Language :: Python :: 3.13
Classifier: Topic :: Software Development :: Libraries :: Python Modules
Requires-Dist: aiohttp (>=3.11.1,<4.0.0)
Project-URL: Repository, https://github.com/ChefJodlak/jito-async
